{
  "generator-jhipster": {
    "applicationType": "monolith",
    "authenticationType": "jwt",
    "baseName": "designer",
    "buildTool": "gradle",
    "cacheProvider": "ehcache",
    "clientFramework": "angular",
    "clientTestFrameworks": [],
    "clientTheme": "none",
    "creationTimestamp": 1753412496969,
    "databaseType": "sql",
    "devDatabaseType": "h2Disk",
    "enableGradleEnterprise": false,
    "enableHibernateCache": true,
    "enableTranslation": true,
    "entities": ["Ships", "Fittings", "Weapons", "Defenses", "Cargoes", "Vehicles", "Engines"],
    "feignClient": null,
    "gradleEnterpriseHost": null,
    "jhipsterVersion": "8.11.0",
    "jwtSecretKey": "ZTc5NjkzOWYwMzgyMTEzMTZjZjE4MTA5OTMyMjRlMzUyYzFiYWEzOWNjNGI3Y2M2MTVjNzRkMTYyMjZkN2E3Zjk5MmQ5NzFhYjExZWU0OTk0Yzc1NGIzZGQ4N2QwNWZiYjcwYTcxYzA0NzhjZDQyNDI2NjQ0NDE0NjJjZTM5MGM=",
    "languages": ["en", "fr", "es"],
    "lastLiquibaseTimestamp": 1753496744000,
    "microfrontend": null,
    "microfrontends": [],
    "nativeLanguage": "en",
    "packageName": "com.virtualsoundnw.designer",
    "prodDatabaseType": "mysql",
    "reactive": false,
    "serverPort": null,
    "serviceDiscoveryType": null,
    "syncUserWithIdp": null,
    "testFrameworks": ["gatling", "cucumber"],
    "withAdminUi": true
  }
}
